loris_log/__init__.py
loris_log/boto3Client.py
loris_log/customLog.py
loris_log/ftpClient.py
loris_log/myException.py
loris_log-0.2.4.post1.dist-info/LICENSE.txt
loris_log-0.2.4.post1.dist-info/METADATA
loris_log-0.2.4.post1.dist-info/WHEEL
loris_log-0.2.4.post1.dist-info/top_level.txt
loris_log-0.2.4.post1.dist-info/RECORD
