Metadata-Version: 2.1
Name: loris-log
Version: 0.2.4.post1
Summary: Log library to establish communication with FTP server and AWS CloudWatch; as well as to publish log message to these platforms.
Author: Kah Seng, Sze Ling, Stanley
Author-email: Kah Seng <lim0709@gmail.com>, Sze Ling <sltang@handalindah.com.my>, Stanley <stanly@handalindah.com.my>
Project-URL: Homepage, https://github.com/mikelim2/python-logging
Keywords: log,FTP,CloudWatch
Classifier: License :: OSI Approved :: MIT License
Classifier: Programming Language :: Python
Classifier: Programming Language :: Python :: 3
Requires-Python: >=3.10
License-File: LICENSE.txt
Requires-Dist: astroid ==2.15.6
Requires-Dist: boto3 ==1.28.65
Requires-Dist: botocore ==1.31.65
Requires-Dist: build ==1.0.3
Requires-Dist: certifi ==2023.7.22
Requires-Dist: cffi ==1.15.1
Requires-Dist: charset-normalizer ==3.2.0
Requires-Dist: click ==8.1.7
Requires-Dist: coverage ==7.3.0
Requires-Dist: cryptography ==41.0.4
Requires-Dist: dill ==0.3.7
Requires-Dist: docutils ==0.20.1
Requires-Dist: idna ==3.4
Requires-Dist: importlib-metadata ==6.8.0
Requires-Dist: isort ==5.12.0
Requires-Dist: jaraco.classes ==3.3.0
Requires-Dist: jeepney ==0.8.0
Requires-Dist: Jinja2 ==3.1.2
Requires-Dist: jmespath ==1.0.1
Requires-Dist: keyring ==24.2.0
Requires-Dist: keyrings.alt ==5.0.0
Requires-Dist: lazy-object-proxy ==1.9.0
Requires-Dist: markdown-it-py ==3.0.0
Requires-Dist: MarkupSafe ==2.1.3
Requires-Dist: mccabe ==0.7.0
Requires-Dist: mdurl ==0.1.2
Requires-Dist: more-itertools ==10.1.0
Requires-Dist: nh3 ==0.2.14
Requires-Dist: packaging ==23.1
Requires-Dist: pdoc ==14.1.0
Requires-Dist: pip-tools ==7.3.0
Requires-Dist: pkginfo ==1.9.6
Requires-Dist: platformdirs ==3.10.0
Requires-Dist: pycparser ==2.21
Requires-Dist: Pygments ==2.16.1
Requires-Dist: pylint ==2.17.5
Requires-Dist: pyproject-hooks ==1.0.0
Requires-Dist: python-dateutil ==2.8.2
Requires-Dist: pytz ==2023.3.post1
Requires-Dist: PyYAML ==6.0.1
Requires-Dist: readme-renderer ==42.0
Requires-Dist: requests ==2.31.0
Requires-Dist: requests-toolbelt ==1.0.0
Requires-Dist: rfc3986 ==2.0.0
Requires-Dist: rich ==13.5.3
Requires-Dist: s3transfer ==0.7.0
Requires-Dist: SecretStorage ==3.3.3
Requires-Dist: six ==1.16.0
Requires-Dist: tomli ==2.0.1
Requires-Dist: tomlkit ==0.12.1
Requires-Dist: twine ==4.0.2
Requires-Dist: typing-extensions ==4.7.1
Requires-Dist: urllib3 ==2.0.7
Requires-Dist: wrapt ==1.15.0
Requires-Dist: zipp ==3.17.0
